<?xml version="1.0" encoding="UTF-8"?>

<!-- generated on Wed Jan 27 08:56:01 2021 by Eclipse SUMO netconvert Version v1_1_0+0000-2147d155b1
<configuration xmlns:xsi="http://www.w3.org/2001/XMLSchema-instance" xsi:noNamespaceSchemaLocation="http://sumo.dlr.de/xsd/netconvertConfiguration.xsd">

    <input>
        <node-files value="./sumo/15/nod.xml"/>
        <edge-files value="./sumo/15/edg.xml"/>
        <connection-files value="./sumo/15/con.xml"/>
    </input>

    <output>
        <output-file value="./sumo/15/net.xml"/>
    </output>

    <junctions>
        <no-turnarounds value="true"/>
    </junctions>

</configuration>
-->

<net version="1.1" junctionCornerDetail="5" limitTurnSpeed="5.50" xmlns:xsi="http://www.w3.org/2001/XMLSchema-instance" xsi:noNamespaceSchemaLocation="http://sumo.dlr.de/xsd/net_file.xsd">

    <location netOffset="0.00,0.00" convBoundary="0.00,0.00,200.00,200.00" origBoundary="0.00,0.00,200.00,200.00" projParameter="!"/>

    <edge id=":n_100.100_0" function="internal">
        <lane id=":n_100.100_0_0" index="0" speed="13.00" length="14.40" shape="98.40,107.20 98.40,92.80"/>
    </edge>
    <edge id=":n_100.100_1" function="internal">
        <lane id=":n_100.100_1_0" index="0" speed="13.00" length="14.40" shape="107.20,101.60 92.80,101.60"/>
    </edge>
    <edge id=":n_100.100_2" function="internal">
        <lane id=":n_100.100_2_0" index="0" speed="13.00" length="14.40" shape="101.60,92.80 101.60,107.20"/>
    </edge>
    <edge id=":n_100.100_3" function="internal">
        <lane id=":n_100.100_3_0" index="0" speed="13.00" length="14.40" shape="92.80,98.40 107.20,98.40"/>
    </edge>

    <edge id="e_0.100_100.100" from="n_0.100" to="n_100.100" priority="-1" length="100.00">
        <lane id="e_0.100_100.100_0" index="0" speed="13.00" length="100.00" shape="0.00,98.40 92.80,98.40"/>
    </edge>
    <edge id="e_100.0_100.100" from="n_100.0" to="n_100.100" priority="-1" length="100.00">
        <lane id="e_100.0_100.100_0" index="0" speed="13.00" length="100.00" shape="101.60,0.00 101.60,92.80"/>
    </edge>
    <edge id="e_100.100_0.100" from="n_100.100" to="n_0.100" priority="-1" length="100.00">
        <lane id="e_100.100_0.100_0" index="0" speed="13.00" length="100.00" shape="92.80,101.60 0.00,101.60"/>
    </edge>
    <edge id="e_100.100_100.0" from="n_100.100" to="n_100.0" priority="-1" length="100.00">
        <lane id="e_100.100_100.0_0" index="0" speed="13.00" length="100.00" shape="98.40,92.80 98.40,0.00"/>
    </edge>
    <edge id="e_100.100_100.200" from="n_100.100" to="n_100.200" priority="-1" length="100.00">
        <lane id="e_100.100_100.200_0" index="0" speed="13.00" length="100.00" shape="101.60,107.20 101.60,200.00"/>
    </edge>
    <edge id="e_100.100_200.100" from="n_100.100" to="n_200.100" priority="-1" length="100.00">
        <lane id="e_100.100_200.100_0" index="0" speed="13.00" length="100.00" shape="107.20,98.40 200.00,98.40"/>
    </edge>
    <edge id="e_100.200_100.100" from="n_100.200" to="n_100.100" priority="-1" length="100.00">
        <lane id="e_100.200_100.100_0" index="0" speed="13.00" length="100.00" shape="98.40,200.00 98.40,107.20"/>
    </edge>
    <edge id="e_200.100_100.100" from="n_200.100" to="n_100.100" priority="-1" length="100.00">
        <lane id="e_200.100_100.100_0" index="0" speed="13.00" length="100.00" shape="200.00,101.60 107.20,101.60"/>
    </edge>

    <junction id="n_0.100" type="dead_end" x="0.00" y="100.00" incLanes="e_100.100_0.100_0" intLanes="" shape="0.00,100.00 0.00,103.20 0.00,100.00"/>
    <junction id="n_100.0" type="dead_end" x="100.00" y="0.00" incLanes="e_100.100_100.0_0" intLanes="" shape="100.00,0.00 96.80,0.00 100.00,0.00"/>
    <junction id="n_100.100" type="priority" x="100.00" y="100.00" incLanes="e_100.200_100.100_0 e_200.100_100.100_0 e_100.0_100.100_0 e_0.100_100.100_0" intLanes=":n_100.100_0_0 :n_100.100_1_0 :n_100.100_2_0 :n_100.100_3_0" shape="96.80,107.20 103.20,107.20 103.64,104.98 104.20,104.20 104.98,103.64 105.98,103.31 107.20,103.20 107.20,96.80 104.98,96.36 104.20,95.80 103.64,95.02 103.31,94.02 103.20,92.80 96.80,92.80 96.36,95.02 95.80,95.80 95.02,96.36 94.02,96.69 92.80,96.80 92.80,103.20 95.02,103.64 95.80,104.20 96.36,104.98 96.69,105.98">
        <request index="0" response="0000" foes="1010" cont="0"/>
        <request index="1" response="0101" foes="0101" cont="0"/>
        <request index="2" response="0000" foes="1010" cont="0"/>
        <request index="3" response="0101" foes="0101" cont="0"/>
    </junction>
    <junction id="n_100.200" type="dead_end" x="100.00" y="200.00" incLanes="e_100.100_100.200_0" intLanes="" shape="100.00,200.00 103.20,200.00 100.00,200.00"/>
    <junction id="n_200.100" type="dead_end" x="200.00" y="100.00" incLanes="e_100.100_200.100_0" intLanes="" shape="200.00,100.00 200.00,96.80 200.00,100.00"/>

    <connection from="e_0.100_100.100" to="e_100.100_200.100" fromLane="0" toLane="0" via=":n_100.100_3_0" dir="s" state="m"/>
    <connection from="e_100.0_100.100" to="e_100.100_100.200" fromLane="0" toLane="0" via=":n_100.100_2_0" dir="s" state="M"/>
    <connection from="e_100.200_100.100" to="e_100.100_100.0" fromLane="0" toLane="0" via=":n_100.100_0_0" dir="s" state="M"/>
    <connection from="e_200.100_100.100" to="e_100.100_0.100" fromLane="0" toLane="0" via=":n_100.100_1_0" dir="s" state="m"/>

    <connection from=":n_100.100_0" to="e_100.100_100.0" fromLane="0" toLane="0" dir="s" state="M"/>
    <connection from=":n_100.100_1" to="e_100.100_0.100" fromLane="0" toLane="0" dir="s" state="M"/>
    <connection from=":n_100.100_2" to="e_100.100_100.200" fromLane="0" toLane="0" dir="s" state="M"/>
    <connection from=":n_100.100_3" to="e_100.100_200.100" fromLane="0" toLane="0" dir="s" state="M"/>

</net>
